{"sections":{"163054232991849cd6":{"type":"index-section-text_block","disabled":true,"settings":{"text1":"WELCOME!","text2":"ABOUT OUR STORE","center_b_d":true,"text3":"Lorem ipsum dolor sit amet conse ctetur adipisicing elit, sed do eiusmod tempor incididunt ut labore et dolore magna aliqua. Ut enim ad minim veniam, quis nostrud exercitation ullamco laboris nisi ut aliquip ex ea commodo consequat. Duis aute irure dolor in reprehenderit in voluptate velit esse."}},"1630541853069ada29":{"type":"index-section-brands","disabled":true,"blocks":{"1630541853069ada29-0":{"type":"logo_image","settings":{"image":"shopify:\/\/shop_images\/volcom_af7ba94c-6402-474c-9f85-cb47593de8a2.png","link":""}},"1630541853069ada29-1":{"type":"logo_image","settings":{"image":"shopify:\/\/shop_images\/roxy_f893c5b7-fae0-4fa8-a058-83db0a001ff4.png","link":""}},"1630541853069ada29-2":{"type":"logo_image","settings":{"image":"shopify:\/\/shop_images\/rip-curl_55ed6d4b-048b-4bf4-ade2-4a51ef167eee.jpg","link":""}},"1630541853069ada29-3":{"type":"logo_image","settings":{"image":"shopify:\/\/shop_images\/indo-board_799b5f49-04e0-4969-9057-80f318ff0994.png","link":""}},"1630541853069ada29-4":{"type":"logo_image","settings":{"image":"shopify:\/\/shop_images\/rvca_013cd1e1-9d09-4dbd-9843-f56ebfe39e97.png","link":""}},"1630541853069ada29-5":{"type":"logo_image","settings":{"image":"shopify:\/\/shop_images\/body-glove_d1401af2-ff72-4468-81c1-06e4e9da84da.png","link":""}},"1630541853069ada29-6":{"type":"logo_image","settings":{"image":"shopify:\/\/shop_images\/logo-header-300_7f4a456d-75f0-4091-844b-e65026abdff2.png","link":""}}},"block_order":["1630541853069ada29-0","1630541853069ada29-1","1630541853069ada29-2","1630541853069ada29-3","1630541853069ada29-4","1630541853069ada29-5","1630541853069ada29-6"],"settings":{"top_offset":"normal","fullwidth":false,"useimageopacityonhover":false,"show_title":false,"title_to_left":false,"text1":"POPULAR","text2":"CLOTHING BRANDS","toshow":"6","step":"2","module_autoplay":false,"delay_time":"7000"}},"main":{"type":"collection-template","settings":{}},"16318611915d2d64c9":{"type":"brands","blocks":{"16318611915d2d64c9-0":{"type":"logo_image","settings":{"image":"shopify:\/\/shop_images\/volcom_af7ba94c-6402-474c-9f85-cb47593de8a2.png","link":""}},"16318611915d2d64c9-1":{"type":"logo_image","settings":{"image":"shopify:\/\/shop_images\/roxy_f893c5b7-fae0-4fa8-a058-83db0a001ff4.png","link":""}},"16318611915d2d64c9-2":{"type":"logo_image","settings":{"image":"shopify:\/\/shop_images\/rip-curl_55ed6d4b-048b-4bf4-ade2-4a51ef167eee.jpg","link":""}},"16318611915d2d64c9-3":{"type":"logo_image","settings":{"image":"shopify:\/\/shop_images\/indo-board_799b5f49-04e0-4969-9057-80f318ff0994.png","link":""}},"16318611915d2d64c9-4":{"type":"logo_image","settings":{"image":"shopify:\/\/shop_images\/rvca_013cd1e1-9d09-4dbd-9843-f56ebfe39e97.png","link":""}},"16318611915d2d64c9-5":{"type":"logo_image","settings":{"image":"shopify:\/\/shop_images\/body-glove_d1401af2-ff72-4468-81c1-06e4e9da84da.png","link":""}}},"block_order":["16318611915d2d64c9-0","16318611915d2d64c9-1","16318611915d2d64c9-2","16318611915d2d64c9-3","16318611915d2d64c9-4","16318611915d2d64c9-5"],"settings":{"show_title":false,"title_to_left":false,"text1":"POPULAR","text2":"CLOTHING BRANDS","toshow":"6","step":"2","module_autoplay":false,"delay_time":"7000"}}},"order":["163054232991849cd6","1630541853069ada29","main","16318611915d2d64c9"]}